<?xml version="1.0" encoding="UTF-8"?>
<ti:work xmlns:ti="http://chs.harvard.edu/xmlns/cts" urn="urn:cts:greekLit:tlg0085.tlg005" xml:lang="grc" groupUrn="urn:cts:greekLit:tlg0085">
   <ti:title xml:lang="eng">Agamemnon</ti:title>
   <ti:edition xml:lang="grc" workUrn="urn:cts:greekLit:tlg0085.tlg005" urn="urn:cts:greekLit:tlg0085.tlg005.daphne-grc1">
      <ti:label xml:lang="eng">Agamemnon</ti:label>
      <ti:description xml:lang="eng">Text prepared for treebank annotation in the Daphne project by F. Mambrini.</ti:description>
   </ti:edition>
  
</ti:work>
